{"201624066310": [], "201622056688": [], "201622056687": [], "201624065990": [], "201614054463": [{"dc_number": "1614054463", "short_caption": "Comm. v. Fauntleroy, Elijah", "otn": "U0425703", "court_summary_url": "https://ujsportal.pacourts.us/Report/CpCourtSummary?docketNumber=MC-51-CR-0019754-2016&dnh=JDVT4D6ehHtVb%2FB7bnQLNQ%3D%3D", "court_type": "Common Pleas", "party": "Fauntleroy, Elijah", "case_status": "Closed", "filing_date": "07/07/2016", "docket_number": "MC-51-CR-0019754-2016", "lotn": "", "court_office": "MC-01-51-Crim", "docket_sheet_url": "https://ujsportal.pacourts.us/Report/CpDocketSheet?docketNumber=MC-51-CR-0019754-2016&dnh=JDVT4D6ehHtVb%2FB7bnQLNQ%3D%3D", "date_of_birth": "06/25/1999", "county": "Philadelphia"}], "201625056577": [], "201639055295": [], "201614054386": [], "201625056307": [], "201615065412": [], "201615065315": [{"dc_number": "1615065315", "short_caption": "Comm. v. PEREZ, ROMEO", "otn": "U0498912", "court_summary_url": "https://ujsportal.pacourts.us/Report/CpCourtSummary?docketNumber=MC-51-CR-0025959-2016&dnh=4BltoTn9EckxudsTzYfFSw%3D%3D", "court_type": "Common Pleas", "party": "PEREZ, ROMEO", "case_status": "Closed", "filing_date": "09/15/2016", "docket_number": "MC-51-CR-0025959-2016", "lotn": "", "court_office": "MC-01-51-Crim", "docket_sheet_url": "https://ujsportal.pacourts.us/Report/CpDocketSheet?docketNumber=MC-51-CR-0025959-2016&dnh=4BltoTn9EckxudsTzYfFSw%3D%3D", "date_of_birth": "05/13/1997", "county": "Philadelphia"}, {"dc_number": "", "short_caption": "", "otn": "", "court_summary_url": "https://ujsportal.pacourts.us/Report/CpCourtSummary?docketNumber=CP-51-CR-0009983-2016&dnh=v1tZQc5bbIjszxH3IXVNrA%3D%3D", "court_type": "", "party": "", "case_status": "", "filing_date": "", "docket_number": "", "lotn": "", "court_office": "", "docket_sheet_url": "https://ujsportal.pacourts.us/Report/CpDocketSheet?docketNumber=CP-51-CR-0009983-2016&dnh=v1tZQc5bbIjszxH3IXVNrA%3D%3D", "date_of_birth": "", "county": ""}], "201639055101": [], "201622056094": [], "201622056090": [], "201617030355": [], "201639054838": [], "201624065342": [], "201622055913": [], "201624065058": [{"dc_number": "1624065058", "short_caption": "Comm. v. Lozada, Markeith", "otn": "U0661231", "court_summary_url": "https://ujsportal.pacourts.us/Report/CpCourtSummary?docketNumber=MC-51-CR-0003053-2017&dnh=YYMQJjrvNt%2FGvY4JKbIkOA%3D%3D", "court_type": "Common Pleas", "party": "Lozada, Markeith", "case_status": "Closed", "filing_date": "02/02/2017", "docket_number": "MC-51-CR-0003053-2017", "lotn": "", "court_office": "MC-01-51-Crim", "docket_sheet_url": "https://ujsportal.pacourts.us/Report/CpDocketSheet?docketNumber=MC-51-CR-0003053-2017&dnh=YYMQJjrvNt%2FGvY4JKbIkOA%3D%3D", "date_of_birth": "11/07/1987", "county": "Philadelphia"}, {"dc_number": "", "short_caption": "", "otn": "", "court_summary_url": "https://ujsportal.pacourts.us/Report/CpCourtSummary?docketNumber=CP-51-CR-0002736-2017&dnh=Wm7pJOt4J9AXoRsgfz5MEw%3D%3D", "court_type": "", "party": "", "case_status": "", "filing_date": "", "docket_number": "", "lotn": "", "court_office": "", "docket_sheet_url": "https://ujsportal.pacourts.us/Report/CpDocketSheet?docketNumber=CP-51-CR-0002736-2017&dnh=Wm7pJOt4J9AXoRsgfz5MEw%3D%3D", "date_of_birth": "", "county": ""}], "201625055708": [], "201612047198": [], "201616028152": [], "201622055399": [], "201614053085": [], "201625055194": [], "201617029849": [], "201617029851": [], "201624064129": [], "201624063881": [], "201639053334": [], "201639053338": [], "201624063418": [], "201612046174": [], "201622054103": [], "201622054104": [], "201639052876": [], "201619059240": [], "201639052780": [], "201622053910": [], "201618047198": [], "201625053761": [], "201616027340": [], "201635056254": [], "201602038689": [], "201622053600": [], "201639052207": [], "201639052215": [], "201612045350": [], "201614050782": []}