{"201824107154": [], "202008013443": [], "201722043524": [], "201625086447": [], "202139003207": [], "201519090869": [], "202022032167": [{"lotn": "", "short_caption": "Comm. v. Hassan, Rashid", "county": "Philadelphia", "party": "Hassan, Rashid", "court_type": "Common Pleas", "date_of_birth": "04/29/1992", "court_office": "MC-01-51-Crim", "docket_sheet_url": "https://ujsportal.pacourts.us/Report/CpDocketSheet?docketNumber=MC-51-CR-0010168-2020&dnh=51s%2FDwZsnUS4YuQWmfIxOQ%3D%3D", "dc_number": "2022032167", "filing_date": "05/28/2020", "otn": "U2043790", "case_status": "Closed", "court_summary_url": "https://ujsportal.pacourts.us/Report/CpCourtSummary?docketNumber=MC-51-CR-0010168-2020&dnh=51s%2FDwZsnUS4YuQWmfIxOQ%3D%3D", "docket_number": "MC-51-CR-0010168-2020"}, {"lotn": "", "short_caption": "", "county": "", "party": "", "court_type": "", "date_of_birth": "", "court_office": "", "docket_sheet_url": "https://ujsportal.pacourts.us/Report/CpDocketSheet?docketNumber=CP-51-CR-0002887-2020&dnh=AO%2FFvoT5OH2ZwnByLGpU1A%3D%3D", "dc_number": "", "filing_date": "", "otn": "", "case_status": "", "court_summary_url": "https://ujsportal.pacourts.us/Report/CpCourtSummary?docketNumber=CP-51-CR-0002887-2020&dnh=AO%2FFvoT5OH2ZwnByLGpU1A%3D%3D", "docket_number": ""}], "201716001809": [], "201735010549": [], "201925018047": []}