{
"type": "FeatureCollection",
"crs": { "type": "name", "properties": { "name": "urn:ogc:def:crs:OGC:1.3:CRS84" } },
"features": [
{ "type": "Feature", "properties": { "dc_key": "202519000703", "race": "W", "sex": "M", "fatal": false, "date": "2025/01/04 21:23:00", "age_group": "18 to 30", "has_court_case": false, "age": 21.0, "street_name": "WYNNEWOOD RD", "block_number": 800.0, "zip_code": "19151", "council_district": "4", "police_district": "19", "neighborhood": "Haddington-Overbrook", "school_name": "Lewis C. Cassidy Academics Plus School", "house_district": "192", "senate_district": "7", "segment_id": "23911" }, "geometry": { "type": "Point", "coordinates": [ -75.247292, 39.977418 ] } },
{ "type": "Feature", "properties": { "dc_key": "202514000921", "race": "B", "sex": "M", "fatal": false, "date": "2025/01/04 20:08:00", "age_group": "18 to 30", "has_court_case": false, "age": 24.0, "street_name": "E PHIL ELLENA ST", "block_number": 200.0, "zip_code": "19119", "council_district": "8", "police_district": "14", "neighborhood": "East Mt. Airy", "school_name": "Eleanor C. Emlen School", "house_district": "200", "senate_district": "4", "segment_id": "4746" }, "geometry": { "type": "Point", "coordinates": [ -75.182554, 40.054327 ] } },
{ "type": "Feature", "properties": { "dc_key": "202525000746", "race": "B", "sex": "M", "fatal": false, "date": "2025/01/04 18:44:00", "age_group": "31 to 45", "has_court_case": false, "age": 38.0, "street_name": "N WARNOCK ST", "block_number": 3500.0, "zip_code": "19140", "council_district": "5", "police_district": "25", "neighborhood": "Hunting Park-Fairhill", "school_name": "Mary M. Bethune School", "house_district": "197", "senate_district": "3", "segment_id": "14113" }, "geometry": { "type": "Point", "coordinates": [ -75.145695, 40.006616 ] } },
{ "type": "Feature", "properties": { "dc_key": "202507000303", "race": "B", "sex": "M", "fatal": false, "date": "2025/01/04 13:08:00", "age_group": "31 to 45", "has_court_case": false, "age": 34.0, "street_name": "PHILMONT AVE", "block_number": 13600.0, "zip_code": "19116", "council_district": "10", "police_district": "7", "neighborhood": "Somerton", "school_name": "Watson Comly School", "house_district": "170", "senate_district": "5", "segment_id": "15261" }, "geometry": { "type": "Point", "coordinates": [ -75.010115, 40.132085 ] } },
{ "type": "Feature", "properties": { "dc_key": "202514000528", "race": "B", "sex": "F", "fatal": false, "date": "2025/01/02 23:21:00", "age_group": "18 to 30", "has_court_case": false, "age": 26.0, "street_name": "W UPSAL ST", "block_number": 200.0, "zip_code": "19119", "council_district": "8", "police_district": "14", "neighborhood": "Chestnut Hill-West Mt. Airy", "school_name": "Anna L. Lingelbach School", "house_district": "200", "senate_district": "4", "segment_id": "22621" }, "geometry": { "type": "Point", "coordinates": [ -75.188952, 40.042827 ] } },
{ "type": "Feature", "properties": { "dc_key": "202515000310", "race": "B", "sex": "M", "fatal": true, "date": "2025/01/02 10:19:00", "age_group": "18 to 30", "has_court_case": false, "age": 26.0, "street_name": "WAKELING ST", "block_number": 1800.0, "zip_code": "19124", "council_district": "7", "police_district": "15", "neighborhood": "Frankford", "school_name": "Mastery Charter School at Smedley", "house_district": "179", "senate_district": "2", "segment_id": "22833" }, "geometry": { "type": "Point", "coordinates": [ -75.075315, 40.01759 ] } },
{ "type": "Feature", "properties": { "dc_key": "202518000068", "race": "B", "sex": "M", "fatal": false, "date": "2025/01/01 11:46:00", "age_group": "18 to 30", "has_court_case": true, "age": 20.0, "street_name": "LATONA ST", "block_number": 5900.0, "zip_code": "19143", "council_district": "3", "police_district": "18", "neighborhood": "Cobbs Creek", "school_name": "Add B. Anderson School", "house_district": "191", "senate_district": "8", "segment_id": "8870" }, "geometry": { "type": "Point", "coordinates": [ -75.242576, 39.94541 ] } },
{ "type": "Feature", "properties": { "dc_key": "202525000052", "race": "W", "sex": "M", "fatal": false, "date": "2025/01/01 03:21:00", "age_group": "Older than 45", "has_court_case": false, "age": 47.0, "street_name": "E ROCKLAND ST", "block_number": 300.0, "zip_code": "19120", "council_district": "7", "police_district": "25", "neighborhood": "Olney-Feltonville", "school_name": "Clara Barton School", "house_district": "197", "senate_district": "3", "segment_id": "4798" }, "geometry": { "type": "Point", "coordinates": [ -75.119768, 40.024109 ] } },
{ "type": "Feature", "properties": { "dc_key": "202512000002", "race": "B", "sex": "M", "fatal": true, "date": "2025/01/01 00:04:00", "age_group": "Older than 45", "has_court_case": false, "age": 54.0, "street_name": "S EDGEWOOD ST", "block_number": 1800.0, "zip_code": "19142", "council_district": "2", "police_district": "12", "neighborhood": "Paschall-Kingsessing", "school_name": "S. Weir Mitchell School", "house_district": "191", "senate_district": "8", "segment_id": "18240" }, "geometry": { "type": "Point", "coordinates": [ -75.232647, 39.933093 ] } }
]
}
